CHANGELOG.txt
LICENCE.txt
MANIFEST.in
README.md
setup.py
tigitaalconnect/__init__.py
tigitaalconnect.egg-info/PKG-INFO
tigitaalconnect.egg-info/SOURCES.txt
tigitaalconnect.egg-info/dependency_links.txt
tigitaalconnect.egg-info/requires.txt
tigitaalconnect.egg-info/top_level.txt