Metadata-Version: 2.1
Name: tigitaalconnect
Version: 0.0.6
Summary: Tigitaal's Official Python Package to connect with TigitaalAPI
Author: Ninjagor
Author-email: ninjagor.spoon@gmail.com
Keywords: python,first package
Classifier: Development Status :: 5 - Production/Stable
Classifier: Intended Audience :: Developers
Classifier: Programming Language :: Python :: 3
Classifier: Operating System :: MacOS :: MacOS X
Classifier: Operating System :: Microsoft :: Windows
License-File: LICENCE.txt
